{"inkVersion":21,"root":[[{"->":"Test"},["done",{"#f":5,"#n":"g-0"}],null],"done",{"Test":[["^Hey Dawg.","\n","ev","str","^Well aren't YOU a fat fuck?","/str","/ev",{"*":".^.c-0","flg":4},"ev","str","^Yo yo!","/str","/ev",{"*":".^.c-1","flg":4},"ev","str","^Omg another idiot.","/str","/ev",{"*":".^.c-2","flg":4},{"c-0":["^ ","\n",{"->":"Anger"},{"#f":5}],"c-1":["\n",{"->":"Smartass"},{"#f":5}],"c-2":["\n",{"->":"Fear"},{"#f":5}]}],{"#f":1}],"Anger":[["^FUCK OFF CUNT.","\n","ev","str","^YEAH FUCK OFF TOO","/str","/ev",{"*":".^.c-0","flg":4},"ev","str","^BITCH ASS","/str","/ev",{"*":".^.c-1","flg":4},"ev","str","^PISS OFF","/str","/ev",{"*":".^.c-2","flg":4},{"c-0":["\n",{"->":"endtest"},{"#f":5}],"c-1":["\n",{"->":"endtest"},{"#f":5}],"c-2":["\n",{"->":"endtest"},{"#f":5}]}],{"#f":1}],"Smartass":[["^How's your cunt!","\n","ev","str","^YEAH FUCK OFF TOO","/str","/ev",{"*":".^.c-0","flg":4},"ev","str","^BITCH ASS","/str","/ev",{"*":".^.c-1","flg":4},"ev","str","^PISS OFF","/str","/ev",{"*":".^.c-2","flg":4},{"c-0":["\n",{"->":"endtest"},{"#f":5}],"c-1":["\n",{"->":"endtest"},{"#f":5}],"c-2":["\n",{"->":"endtest"},{"#f":5}]}],{"#f":1}],"Fear":[["^Oh no you got my dicklet.","\n","ev","str","^YEAH FUCK OFF TOO","/str","/ev",{"*":".^.c-0","flg":4},"ev","str","^BITCH ASS","/str","/ev",{"*":".^.c-1","flg":4},"ev","str","^PISS OFF","/str","/ev",{"*":".^.c-2","flg":4},{"c-0":["\n",{"->":"endtest"},{"#f":5}],"c-1":["\n",{"->":"endtest"},{"#f":5}],"c-2":["\n",{"->":"endtest"},{"#f":5}]}],{"#f":1}],"endtest":["^BITCH ASS NIGGA","\n","end",{"#f":1}],"#f":1}],"listDefs":{}}